{
    "_sideBarDownloadAnchor" : "Download with Nuget",
    "_sideBarDownloadLink" : "https://www.nuget.org/packages/IronOcr/",
    "_sideBarFreeDownloadAnchor" : "Start for Free",
    "_sideBarFreeDownloadLink" : "#trial-license",
    "_modalWindowLicensingLink" : "/csharp/ocr/licensing/",
    "_productName" : "IronOCR",
    "_hubspotFormID" : "43eca219-1649-4e89-a2af-f0540d77df01",
    "_modalWindowProductImage" : "https://ironsoftware.com/img/products/ironocr-logo.svg",
    "_modalWindowCSSForTheImage" : "background-size: 511px; background-position: top 61px left -335px;",
    "_thanksModalWindowCSSForTheImage" : "background-size: 511px; background-position: top 13px left -229px;"
}
