{
    "_sideBarDownloadAnchor" : "Download with Nuget",
    "_sideBarDownloadLink" : "https://www.nuget.org/packages/IronWebScraper/",
    "_sideBarFreeDownloadAnchor" : "Start for Free",
    "_sideBarFreeDownloadLink" : "#trial-license",
    "_modalWindowLicensingLink" : "/csharp/webscraper/licensing/",
    "_productName" : "IronWebscraper",
    "_hubspotFormID" : "b29ae6f3-aba5-4aed-a432-4dd47242aa72",
    "_modalWindowProductImage" : "https://ironsoftware.com/img/products/ironwebscraper-logo-rotated.svg",
    "_modalWindowCSSForTheImage" : "background-size: 456px; background-position: top 20px left -286px;",
    "_thanksModalWindowCSSForTheImage" : "background-size: 356px; background-position: top 23px left -73px;"
}
